opencompass/__init__.py
opencompass/registry.py
opencompass/cli/__init__.py
opencompass/cli/arguments.py
opencompass/cli/main.py
opencompass/configs/__init__.py
opencompass/configs/eval_TheoremQA.py
opencompass/configs/eval_academic_leaderboard_202407.py
opencompass/configs/eval_alaya.py
opencompass/configs/eval_api_demo.py
opencompass/configs/eval_attack.py
opencompass/configs/eval_base_demo.py
opencompass/configs/eval_bluelm_32k_lveval.py
opencompass/configs/eval_charm_mem.py
opencompass/configs/eval_charm_rea.py
opencompass/configs/eval_chat_agent.py
opencompass/configs/eval_chat_agent_baseline.py
opencompass/configs/eval_chat_demo.py
opencompass/configs/eval_chat_last.py
opencompass/configs/eval_chembench.py
opencompass/configs/eval_cibench.py
opencompass/configs/eval_cibench_api.py
opencompass/configs/eval_circular.py
opencompass/configs/eval_claude.py
opencompass/configs/eval_code_passk.py
opencompass/configs/eval_code_passk_repeat_dataset.py
opencompass/configs/eval_codeagent.py
opencompass/configs/eval_codegeex2.py
opencompass/configs/eval_contamination.py
opencompass/configs/eval_demo.py
opencompass/configs/eval_ds1000_interpreter.py
opencompass/configs/eval_edgellm_demo.py
opencompass/configs/eval_gpt3.5.py
opencompass/configs/eval_gpt4.py
opencompass/configs/eval_hf_llama2.py
opencompass/configs/eval_hf_llama_7b.py
opencompass/configs/eval_inference_ppl.py
opencompass/configs/eval_internLM.py
opencompass/configs/eval_internlm2_chat_keyset.py
opencompass/configs/eval_internlm2_keyset.py
opencompass/configs/eval_internlm_7b.py
opencompass/configs/eval_internlm_chat_lmdeploy_apiserver.py
opencompass/configs/eval_internlm_chat_lmdeploy_pytorch.py
opencompass/configs/eval_internlm_chat_lmdeploy_tis.py
opencompass/configs/eval_internlm_chat_turbomind.py
opencompass/configs/eval_internlm_chat_turbomind_tis.py
opencompass/configs/eval_internlm_flames_chat.py
opencompass/configs/eval_internlm_lmdeploy_apiserver.py
opencompass/configs/eval_internlm_math_chat.py
ms_opencompass-0.1.3.dist-info/METADATA
ms_opencompass-0.1.3.dist-info/WHEEL
ms_opencompass-0.1.3.dist-info/entry_points.txt
ms_opencompass-0.1.3.dist-info/top_level.txt
ms_opencompass-0.1.3.dist-info/RECORD
