Metadata-Version: 2.1
Name: ms-opencompass
Version: 0.1.3
Summary: A lightweight toolkit for evaluating LLMs based on OpenCompass.
Home-page: https://github.com/wangxingjun778/opencompass
Author: OpenCompass Contributors
Maintainer: OpenCompass Authors, ModelScope Contributors
License: Apache License 2.0
Keywords: AI,NLP,in-context learning,large language model,evaluation,benchmark,llm
Classifier: Programming Language :: Python :: 3.8
Classifier: Programming Language :: Python :: 3.9
Classifier: Programming Language :: Python :: 3.10
Classifier: Intended Audience :: Developers
Classifier: Intended Audience :: Education
Classifier: Intended Audience :: Science/Research
Requires-Python: >=3.8.0
Requires-Dist: absl-py
Requires-Dist: accelerate (>=0.19.0)
Requires-Dist: cpm-kernels
Requires-Dist: datasets (>=2.18.0)
Requires-Dist: einops
Requires-Dist: evaluate (>=0.3.0)
Requires-Dist: func-timeout
Requires-Dist: fuzzywuzzy
Requires-Dist: h5py
Requires-Dist: immutabledict
Requires-Dist: jieba
Requires-Dist: json5
Requires-Dist: mmengine-lite
Requires-Dist: nltk
Requires-Dist: numpy (>=1.23.4)
Requires-Dist: numpy (<2.0.0,>=1.23.4)
Requires-Dist: openai
Requires-Dist: OpenCC
Requires-Dist: pandas
Requires-Dist: prettytable
Requires-Dist: protobuf
Requires-Dist: pypinyin
Requires-Dist: python-Levenshtein
Requires-Dist: rank-bm25
Requires-Dist: rapidfuzz
Requires-Dist: requests
Requires-Dist: rich
Requires-Dist: rouge
Requires-Dist: rouge-chinese
Requires-Dist: rouge-score
Requires-Dist: sacrebleu
Requires-Dist: scikit-learn
Requires-Dist: seaborn
Requires-Dist: sentence-transformers
Requires-Dist: tabulate
Requires-Dist: tiktoken
Requires-Dist: timeout-decorator
Requires-Dist: tokenizers (>=0.13.3)
Requires-Dist: torch (>=1.13.1)
Requires-Dist: tqdm
Requires-Dist: transformers (>=4.29.1)
Requires-Dist: typer
Requires-Dist: dacite
Requires-Dist: human-eval
Provides-Extra: api
Requires-Dist: anthropic ; extra == 'api'
Requires-Dist: dashscope ; extra == 'api'
Requires-Dist: openai ; extra == 'api'
Requires-Dist: spark-ai-python ; extra == 'api'
Requires-Dist: sseclient-py (==1.7.2) ; extra == 'api'
Requires-Dist: tencentcloud-sdk-python ; extra == 'api'
Requires-Dist: volcengine ; extra == 'api'
Requires-Dist: volcengine-python-sdk ; extra == 'api'
Requires-Dist: websocket-client ; extra == 'api'
Requires-Dist: zhipuai ; extra == 'api'
Requires-Dist: absl-py ; extra == 'api'
Requires-Dist: accelerate (>=0.19.0) ; extra == 'api'
Requires-Dist: cpm-kernels ; extra == 'api'
Requires-Dist: datasets (>=2.18.0) ; extra == 'api'
Requires-Dist: einops ; extra == 'api'
Requires-Dist: evaluate (>=0.3.0) ; extra == 'api'
Requires-Dist: func-timeout ; extra == 'api'
Requires-Dist: fuzzywuzzy ; extra == 'api'
Requires-Dist: h5py ; extra == 'api'
Requires-Dist: immutabledict ; extra == 'api'
Requires-Dist: jieba ; extra == 'api'
Requires-Dist: json5 ; extra == 'api'
Requires-Dist: mmengine-lite ; extra == 'api'
Requires-Dist: nltk ; extra == 'api'
Requires-Dist: numpy (>=1.23.4) ; extra == 'api'
Requires-Dist: numpy (<2.0.0,>=1.23.4) ; extra == 'api'
Requires-Dist: OpenCC ; extra == 'api'
Requires-Dist: pandas ; extra == 'api'
Requires-Dist: prettytable ; extra == 'api'
Requires-Dist: protobuf ; extra == 'api'
Requires-Dist: pypinyin ; extra == 'api'
Requires-Dist: python-Levenshtein ; extra == 'api'
Requires-Dist: rank-bm25 ; extra == 'api'
Requires-Dist: rapidfuzz ; extra == 'api'
Requires-Dist: requests ; extra == 'api'
Requires-Dist: rich ; extra == 'api'
Requires-Dist: rouge ; extra == 'api'
Requires-Dist: rouge-chinese ; extra == 'api'
Requires-Dist: rouge-score ; extra == 'api'
Requires-Dist: sacrebleu ; extra == 'api'
Requires-Dist: scikit-learn ; extra == 'api'
Requires-Dist: seaborn ; extra == 'api'
Requires-Dist: sentence-transformers ; extra == 'api'
Requires-Dist: tabulate ; extra == 'api'
Requires-Dist: tiktoken ; extra == 'api'
Requires-Dist: timeout-decorator ; extra == 'api'
Requires-Dist: tokenizers (>=0.13.3) ; extra == 'api'
Requires-Dist: torch (>=1.13.1) ; extra == 'api'
Requires-Dist: tqdm ; extra == 'api'
Requires-Dist: transformers (>=4.29.1) ; extra == 'api'
Requires-Dist: typer ; extra == 'api'
Requires-Dist: dacite ; extra == 'api'
Requires-Dist: human-eval ; extra == 'api'
Provides-Extra: full
Requires-Dist: alpaca-eval (==0.6) ; extra == 'full'
Requires-Dist: cn2an ; extra == 'full'
Requires-Dist: faiss-gpu (==1.7.2) ; extra == 'full'
Requires-Dist: human-eval ; extra == 'full'
Requires-Dist: langdetect ; extra == 'full'
Requires-Dist: latex2sympy2 ; extra == 'full'
Requires-Dist: ltp ; extra == 'full'
Requires-Dist: pyext ; extra == 'full'
Requires-Dist: pypinyin ; extra == 'full'
Requires-Dist: wonderwords ; extra == 'full'
Requires-Dist: absl-py ; extra == 'full'
Requires-Dist: accelerate (>=0.19.0) ; extra == 'full'
Requires-Dist: cpm-kernels ; extra == 'full'
Requires-Dist: datasets (>=2.18.0) ; extra == 'full'
Requires-Dist: einops ; extra == 'full'
Requires-Dist: evaluate (>=0.3.0) ; extra == 'full'
Requires-Dist: func-timeout ; extra == 'full'
Requires-Dist: fuzzywuzzy ; extra == 'full'
Requires-Dist: h5py ; extra == 'full'
Requires-Dist: immutabledict ; extra == 'full'
Requires-Dist: jieba ; extra == 'full'
Requires-Dist: json5 ; extra == 'full'
Requires-Dist: mmengine-lite ; extra == 'full'
Requires-Dist: nltk ; extra == 'full'
Requires-Dist: numpy (>=1.23.4) ; extra == 'full'
Requires-Dist: numpy (<2.0.0,>=1.23.4) ; extra == 'full'
Requires-Dist: openai ; extra == 'full'
Requires-Dist: OpenCC ; extra == 'full'
Requires-Dist: pandas ; extra == 'full'
Requires-Dist: prettytable ; extra == 'full'
Requires-Dist: protobuf ; extra == 'full'
Requires-Dist: python-Levenshtein ; extra == 'full'
Requires-Dist: rank-bm25 ; extra == 'full'
Requires-Dist: rapidfuzz ; extra == 'full'
Requires-Dist: requests ; extra == 'full'
Requires-Dist: rich ; extra == 'full'
Requires-Dist: rouge ; extra == 'full'
Requires-Dist: rouge-chinese ; extra == 'full'
Requires-Dist: rouge-score ; extra == 'full'
Requires-Dist: sacrebleu ; extra == 'full'
Requires-Dist: scikit-learn ; extra == 'full'
Requires-Dist: seaborn ; extra == 'full'
Requires-Dist: sentence-transformers ; extra == 'full'
Requires-Dist: tabulate ; extra == 'full'
Requires-Dist: tiktoken ; extra == 'full'
Requires-Dist: timeout-decorator ; extra == 'full'
Requires-Dist: tokenizers (>=0.13.3) ; extra == 'full'
Requires-Dist: torch (>=1.13.1) ; extra == 'full'
Requires-Dist: tqdm ; extra == 'full'
Requires-Dist: transformers (>=4.29.1) ; extra == 'full'
Requires-Dist: typer ; extra == 'full'
Requires-Dist: dacite ; extra == 'full'
Provides-Extra: lmdeploy
Requires-Dist: absl-py ; extra == 'lmdeploy'
Requires-Dist: accelerate (>=0.19.0) ; extra == 'lmdeploy'
Requires-Dist: cpm-kernels ; extra == 'lmdeploy'
Requires-Dist: datasets (>=2.18.0) ; extra == 'lmdeploy'
Requires-Dist: einops ; extra == 'lmdeploy'
Requires-Dist: evaluate (>=0.3.0) ; extra == 'lmdeploy'
Requires-Dist: func-timeout ; extra == 'lmdeploy'
Requires-Dist: fuzzywuzzy ; extra == 'lmdeploy'
Requires-Dist: h5py ; extra == 'lmdeploy'
Requires-Dist: immutabledict ; extra == 'lmdeploy'
Requires-Dist: jieba ; extra == 'lmdeploy'
Requires-Dist: json5 ; extra == 'lmdeploy'
Requires-Dist: mmengine-lite ; extra == 'lmdeploy'
Requires-Dist: nltk ; extra == 'lmdeploy'
Requires-Dist: numpy (>=1.23.4) ; extra == 'lmdeploy'
Requires-Dist: numpy (<2.0.0,>=1.23.4) ; extra == 'lmdeploy'
Requires-Dist: openai ; extra == 'lmdeploy'
Requires-Dist: OpenCC ; extra == 'lmdeploy'
Requires-Dist: pandas ; extra == 'lmdeploy'
Requires-Dist: prettytable ; extra == 'lmdeploy'
Requires-Dist: protobuf ; extra == 'lmdeploy'
Requires-Dist: pypinyin ; extra == 'lmdeploy'
Requires-Dist: python-Levenshtein ; extra == 'lmdeploy'
Requires-Dist: rank-bm25 ; extra == 'lmdeploy'
Requires-Dist: rapidfuzz ; extra == 'lmdeploy'
Requires-Dist: requests ; extra == 'lmdeploy'
Requires-Dist: rich ; extra == 'lmdeploy'
Requires-Dist: rouge ; extra == 'lmdeploy'
Requires-Dist: rouge-chinese ; extra == 'lmdeploy'
Requires-Dist: rouge-score ; extra == 'lmdeploy'
Requires-Dist: sacrebleu ; extra == 'lmdeploy'
Requires-Dist: scikit-learn ; extra == 'lmdeploy'
Requires-Dist: seaborn ; extra == 'lmdeploy'
Requires-Dist: sentence-transformers ; extra == 'lmdeploy'
Requires-Dist: tabulate ; extra == 'lmdeploy'
Requires-Dist: tiktoken ; extra == 'lmdeploy'
Requires-Dist: timeout-decorator ; extra == 'lmdeploy'
Requires-Dist: tokenizers (>=0.13.3) ; extra == 'lmdeploy'
Requires-Dist: torch (>=1.13.1) ; extra == 'lmdeploy'
Requires-Dist: tqdm ; extra == 'lmdeploy'
Requires-Dist: transformers (>=4.29.1) ; extra == 'lmdeploy'
Requires-Dist: typer ; extra == 'lmdeploy'
Requires-Dist: dacite ; extra == 'lmdeploy'
Requires-Dist: human-eval ; extra == 'lmdeploy'
Provides-Extra: vllm
Requires-Dist: absl-py ; extra == 'vllm'
Requires-Dist: accelerate (>=0.19.0) ; extra == 'vllm'
Requires-Dist: cpm-kernels ; extra == 'vllm'
Requires-Dist: datasets (>=2.18.0) ; extra == 'vllm'
Requires-Dist: einops ; extra == 'vllm'
Requires-Dist: evaluate (>=0.3.0) ; extra == 'vllm'
Requires-Dist: func-timeout ; extra == 'vllm'
Requires-Dist: fuzzywuzzy ; extra == 'vllm'
Requires-Dist: h5py ; extra == 'vllm'
Requires-Dist: immutabledict ; extra == 'vllm'
Requires-Dist: jieba ; extra == 'vllm'
Requires-Dist: json5 ; extra == 'vllm'
Requires-Dist: mmengine-lite ; extra == 'vllm'
Requires-Dist: nltk ; extra == 'vllm'
Requires-Dist: numpy (>=1.23.4) ; extra == 'vllm'
Requires-Dist: numpy (<2.0.0,>=1.23.4) ; extra == 'vllm'
Requires-Dist: openai ; extra == 'vllm'
Requires-Dist: OpenCC ; extra == 'vllm'
Requires-Dist: pandas ; extra == 'vllm'
Requires-Dist: prettytable ; extra == 'vllm'
Requires-Dist: protobuf ; extra == 'vllm'
Requires-Dist: pypinyin ; extra == 'vllm'
Requires-Dist: python-Levenshtein ; extra == 'vllm'
Requires-Dist: rank-bm25 ; extra == 'vllm'
Requires-Dist: rapidfuzz ; extra == 'vllm'
Requires-Dist: requests ; extra == 'vllm'
Requires-Dist: rich ; extra == 'vllm'
Requires-Dist: rouge ; extra == 'vllm'
Requires-Dist: rouge-chinese ; extra == 'vllm'
Requires-Dist: rouge-score ; extra == 'vllm'
Requires-Dist: sacrebleu ; extra == 'vllm'
Requires-Dist: scikit-learn ; extra == 'vllm'
Requires-Dist: seaborn ; extra == 'vllm'
Requires-Dist: sentence-transformers ; extra == 'vllm'
Requires-Dist: tabulate ; extra == 'vllm'
Requires-Dist: tiktoken ; extra == 'vllm'
Requires-Dist: timeout-decorator ; extra == 'vllm'
Requires-Dist: tokenizers (>=0.13.3) ; extra == 'vllm'
Requires-Dist: torch (>=1.13.1) ; extra == 'vllm'
Requires-Dist: tqdm ; extra == 'vllm'
Requires-Dist: transformers (>=4.29.1) ; extra == 'vllm'
Requires-Dist: typer ; extra == 'vllm'
Requires-Dist: dacite ; extra == 'vllm'
Requires-Dist: human-eval ; extra == 'vllm'
